dmfrbloom/__init__.py
dmfrbloom/bitfield.py
dmfrbloom/bloomfilter.py
dmfrbloom/pymmh3.py
dmfrbloom/timefilter.py
dmfrbloom-0.0.7.dist-info/LICENSE
dmfrbloom-0.0.7.dist-info/METADATA
dmfrbloom-0.0.7.dist-info/WHEEL
dmfrbloom-0.0.7.dist-info/top_level.txt
dmfrbloom-0.0.7.dist-info/RECORD
