Metadata-Version: 2.1
Name: dmfrbloom
Version: 0.0.7
Summary: Bloom filters with the standard library
Home-page: https://github.com/droberson/dmfrbloom
Author: Daniel Roberson
Author-email: daniel@planethacker.net
License: UNKNOWN
Platform: UNKNOWN
Classifier: Programming Language :: Python :: 3
Classifier: License :: OSI Approved :: MIT License
Classifier: Operating System :: OS Independent
Requires-Python: >=3.6
